AUTHORS
CHANGELOG
LICENSE
MANIFEST.in
README.rst
setup.cfg
setup.py
plans/__init__.py
plans/admin.py
plans/apps.py
plans/conf.py
plans/context_processors.py
plans/contrib.py
plans/enumeration.py
plans/forms.py
plans/importer.py
plans/listeners.py
plans/mixins.py
plans/models.py
plans/plan_change.py
plans/quota.py
plans/signals.py
plans/tasks.py
plans/urls.py
plans/utils.py
plans/validators.py
plans/views.py
plans/fixtures/initial_plan.json
plans/fixtures/test_django-plans_auth.json
plans/fixtures/test_django-plans_default_plans.json
plans/fixtures/test_django-plans_plans.json
plans/locale/en/LC_MESSAGES/django.po
plans/locale/pl/LC_MESSAGES/django.mo
plans/locale/pl/LC_MESSAGES/django.po
plans/locale/pt_BR/LC_MESSAGES/django.mo
plans/locale/pt_BR/LC_MESSAGES/django.po
plans/locale/ru/LC_MESSAGES/django.mo
plans/locale/ru/LC_MESSAGES/django.po
plans/management/__init__.py
plans/management/commands/__init__.py
plans/management/commands/autorenew_accounts.py
plans/management/commands/create_userplans.py
plans/management/commands/expire_accounts.py
plans/migrations/0001_initial.py
plans/migrations/0002_auto_20180901_1744.py
plans/migrations/0003_make_plans_unique.py
plans/migrations/0004_create_user_plans.py
plans/migrations/0005_recurring_payments.py
plans/migrations/0006_auto_20200504_1541.py
plans/migrations/0007_recurringuserplan_card_masked_number.py
plans/migrations/0008_recurringuserplan_token_verified.py
plans/migrations/0009_auto_20210303_1134.py
plans/migrations/0010_auto_20220113_1317.py
plans/migrations/0011_auto_20220208_1344.py
plans/migrations/__init__.py
plans/taxation/__init__.py
plans/taxation/eu.py
plans/taxation/ru.py
plans/templates/mail/change_plan_body.txt
plans/templates/mail/change_plan_title.txt
plans/templates/mail/expired_account_body.txt
plans/templates/mail/expired_account_title.txt
plans/templates/mail/extend_account_body.txt
plans/templates/mail/extend_account_title.txt
plans/templates/mail/invoice_created_body.txt
teson_django_plans.egg-info/PKG-INFO
teson_django_plans.egg-info/SOURCES.txt
teson_django_plans.egg-info/dependency_links.txt
teson_django_plans.egg-info/not-zip-safe
teson_django_plans.egg-info/requires.txt
teson_django_plans.egg-info/top_level.txt