Metadata-Version: 2.1
Name: teson-django-plans
Version: 0.9
Summary: Pluggable django app for managing pricing plans with quotas and accounts expiration
Home-page: https://github.com/tejs1106/django-plans
Author: Tejas Ingale
Author-email: tejasingale1106@gmail.com
License: MIT
Platform: UNKNOWN
Classifier: Development Status :: 4 - Beta
Classifier: Framework :: Django
Classifier: Intended Audience :: Developers
Classifier: License :: OSI Approved :: BSD License
Classifier: Operating System :: OS Independent
Classifier: Programming Language :: Python
Classifier: Programming Language :: Python :: 3.6
Provides-Extra: i18n
